streamlit_google_auth/__init__.py
streamlit_google_auth/cookie/__init__.py
streamlit_google_auth-1.1.7.dist-info/LICENSE
streamlit_google_auth-1.1.7.dist-info/METADATA
streamlit_google_auth-1.1.7.dist-info/WHEEL
streamlit_google_auth-1.1.7.dist-info/top_level.txt
streamlit_google_auth-1.1.7.dist-info/RECORD
