Metadata-Version: 2.1
Name: streamlit-google-auth
Version: 1.1.7
Summary: Use Google authentification in streamlit
Author-email: Adrien Bouvais <adrien.bouvais.pro@gmail.com>
License: MIT License
Project-URL: Homepage, https://github.com/MrBounty/streamlit-google-auth
Keywords: streamlit,google,authentification
Classifier: License :: OSI Approved :: MIT License
Classifier: Programming Language :: Python
Classifier: Programming Language :: Python :: 3
Requires-Python: >=3.9.7
License-File: LICENSE
Requires-Dist: streamlit
Requires-Dist: pyjwt
Requires-Dist: extra-streamlit-components
Requires-Dist: google-auth-oauthlib
Requires-Dist: google-api-python-client
